evtxtract/__init__.py
evtxtract/carvers.py
evtxtract/main.py
evtxtract/templates.py
evtxtract/utils.py
evtxtract/version.py
evtxtract-0.2.3.dist-info/DESCRIPTION.rst
evtxtract-0.2.3.dist-info/METADATA
evtxtract-0.2.3.dist-info/RECORD
evtxtract-0.2.3.dist-info/WHEEL
evtxtract-0.2.3.dist-info/entry_points.txt
evtxtract-0.2.3.dist-info/metadata.json
evtxtract-0.2.3.dist-info/top_level.txt
