Metadata-Version: 2.0
Name: evtxtract
Version: 0.2.3
Summary: EVTXtract recovers and reconstructs fragments of EVTX log files from raw binary data, including unallocated space and memory images.
Home-page: https://github.com/williballenthin/evtxtract
Author: Willi Ballenthin
Author-email: william.ballenthin@fireeye.com
License: Apache 2.0 License
Platform: UNKNOWN
Requires-Dist: six
Requires-Dist: lxml
Requires-Dist: pytest
Requires-Dist: python-evtx (>=0.5.2)
